picofun/__init__.py
picofun/__main__.py
picofun/cli.py
picofun/config.py
picofun/errors.py
picofun/lambda_generator.py
picofun/layer.py
picofun/requirements_manager.py
picofun/spec.py
picofun/template.py
picofun/terraform_generator.py
picofun/templates/lambda.py.j2
picofun/templates/main.tf.j2
picofun-0.4.2.dist-info/LICENSE.txt
picofun-0.4.2.dist-info/METADATA
picofun-0.4.2.dist-info/WHEEL
picofun-0.4.2.dist-info/entry_points.txt
picofun-0.4.2.dist-info/top_level.txt
picofun-0.4.2.dist-info/RECORD
