Metadata-Version: 2.1
Name: picofun
Version: 0.4.2
Summary: PicoFun AWS Lambda generator
Author-email: Dave Hall <skwashd@gmail.com>
License: Copyright 2023 Dave Hall - https://proactiveops.io
License-File: LICENSE.txt
Requires-Dist: black ==24.10.0
Requires-Dist: jinja2 ==3.1.4
Requires-Dist: PyYAML ==6.0.2
Requires-Dist: requests ==2.32.3
Requires-Dist: tomli ==2.0.2
Requires-Dist: typer ==0.12.5
Provides-Extra: build
Requires-Dist: build ==1.2.2.post1 ; extra == 'build'
Requires-Dist: twine ==5.1.1 ; extra == 'build'
Provides-Extra: dev
Requires-Dist: coverage ==7.6.4 ; extra == 'dev'
Requires-Dist: pytest ==8.3.3 ; extra == 'dev'
Requires-Dist: pytest-mock ==3.14.0 ; extra == 'dev'
Requires-Dist: ruff ==0.7.1 ; extra == 'dev'
